eumetsat2ani-0.1.0.dist-info/METADATA
eumetsat2ani-0.1.0.dist-info/WHEEL
eumetsat2ani/__init__.py
eumetsat2ani/__main__.py
eumetsat2ani/fetch.py
eumetsat2ani/render.py
eumetsat2ani/utils.py
eumetsat2ani-0.1.0.dist-info/RECORD
