Metadata-Version: 2.1
Name: eumetsat2ani
Version: 0.1.0
Summary: Create animations directly from EUMETSAT data
Author-Email: Leif Denby <lcd@dmi.dk>
License: MIT
Requires-Python: >=3.9
Requires-Dist: eumdac>=2.0.1
Requires-Dist: setuptools>=68.0.0
Requires-Dist: loguru>=0.7.0
Requires-Dist: satpy>=0.43.0
Requires-Dist: isodate>=0.6.1
Requires-Dist: imageio>=2.31.1
